heprefs/__init__.py
heprefs/__main__.py
heprefs/arxiv_article.py
heprefs/cds_article.py
heprefs/heprefs.py
heprefs/inspire_article.py
heprefs/invenio.py
heprefs-0.1.5.dist-info/entry_points.txt
heprefs-0.1.5.dist-info/LICENSE
heprefs-0.1.5.dist-info/WHEEL
heprefs-0.1.5.dist-info/METADATA
heprefs-0.1.5.dist-info/RECORD
